sas7bdat_converter/__init__.py
sas7bdat_converter/converter.py
sas7bdat_converter/py.typed
sas7bdat_converter-3.0.0.dist-info/METADATA
sas7bdat_converter-3.0.0.dist-info/WHEEL
sas7bdat_converter-3.0.0.dist-info/licenses/LICENSE
sas7bdat_converter-3.0.0.dist-info/RECORD
