Metadata-Version: 2.4
Name: sas7bdat-converter
Version: 3.0.0
Summary: Convert sas7bdat and xport files into other formats
Project-URL: repository, https://github.com/sanders41/sas7bdat-converter
Project-URL: homepage, https://github.com/sanders41/sas7bdat-converter
Project-URL: documentation, https://github.com/sanders41/sas7bdat-converter
Author-email: Paul Sanders <paul@paulsanders.dev>
License: MIT License
License-File: LICENSE
Keywords: XPort,converter,sas,sas7bdat,xpt
Classifier: Development Status :: 5 - Production/Stable
Classifier: License :: OSI Approved :: MIT License
Classifier: Operating System :: OS Independent
Classifier: Programming Language :: Python :: 3.10
Classifier: Programming Language :: Python :: 3.11
Classifier: Programming Language :: Python :: 3.12
Classifier: Programming Language :: Python :: 3.13
Classifier: Typing :: Typed
Requires-Python: >=3.10
Requires-Dist: pandas>=2.0.0
Provides-Extra: all
Requires-Dist: openpyxl>=3.0.5; extra == 'all'
Provides-Extra: openpyxl
Requires-Dist: openpyxl>=3.0.5; extra == 'openpyxl'
